spark_mooc_meta
