Metadata-Version: 1.0
Name: spark-mooc-meta
Version: 1.0.3
Summary: Meta-package for Spark MOOCs; pulls in other packages.
Home-page: UNKNOWN
Author: Databricks, Inc.
Author-email: training-logins@databricks.com
License: Creative Commons Attribution-NonCommercial 4.0 International
Keywords: spark,mooc,databricks
Platform: UNKNOWN
